model_saver/__init__.py
model_saver/modelSaver.py
model_saver-2.9.0.dist-info/LICENSE
model_saver-2.9.0.dist-info/METADATA
model_saver-2.9.0.dist-info/WHEEL
model_saver-2.9.0.dist-info/top_level.txt
model_saver-2.9.0.dist-info/RECORD
