Metadata-Version: 2.1
Name: model-saver
Version: 2.9.0
Summary: A package for saving and loading machine learning models using pickle
Home-page: https://github.com/somkietacode/ModelSaver
Author: somkietacode
Author-email: s.r.a.ouedraogo@gmail.com
Classifier: Development Status :: 5 - Production/Stable
Classifier: Intended Audience :: Developers
Classifier: Intended Audience :: Science/Research
Classifier: License :: OSI Approved :: MIT License
Classifier: Programming Language :: Python :: 3
Classifier: Programming Language :: Python :: 3.6
Classifier: Programming Language :: Python :: 3.7
Classifier: Programming Language :: Python :: 3.8
Classifier: Programming Language :: Python :: 3.9
License-File: LICENSE
